{"id":"G000566","title":"Representative","short_title":"Rep.","api_uri":"https://api.propublica.org/congress/v1/members/G000566.json","first_name":"Trey","middle_name":null,"last_name":"Gowdy","suffix":null,"date_of_birth":"1964-08-22","gender":"M","party":"R","leadership_role":"","twitter_account":"TGowdySC","facebook_account":"143059759084016","youtube_account":"TGowdySC","govtrack_id":"412473","cspan_id":"9268950","votesmart_id":"121782","icpsr_id":"21175","crp_id":"N00030880","google_entity_id":"/m/0c3x3rz","fec_candidate_id":"H0SC04257","url":"https://gowdy.house.gov","rss_url":"https://gowdy.house.gov/rss.xml","contact_form":null,"in_office":true,"dw_nominate":0.664,"ideal_point":null,"seniority":"8","next_election":"2018","total_votes":921,"missed_votes":50,"total_present":0,"ocd_id":"ocd-division/country:us/state:sc/cd:4","office":"2418 Rayburn House Office Building","phone":"202-225-6030","fax":"202-226-1177","state":"SC","district":"4","at_large":false,"geoid":"4504","missed_votes_pct":5.43,"votes_with_party_pct":98.28,"response":{"industries":{"@attributes":{"cand_name":"Trey Gowdy (R)","cid":"N00030880","cycle":"2018","origin":"Center for Responsive Politics","source":"https://www.opensecrets.org/members-of-congress/industries?cid=N00030880&cycle=2018","last_updated":"04/30/2018"},"industry":[{"@attributes":{"industry_code":"W06","industry_name":"Retired","indivs":"205469","pacs":"0","total":"205469"}},{"@attributes":{"industry_code":"Q01","industry_name":"Republican/Conservative","indivs":"85185","pacs":"8700","total":"93885"}},{"@attributes":{"industry_code":"F10","industry_name":"Real Estate","indivs":"24570","pacs":"12900","total":"37470"}},{"@attributes":{"industry_code":"K01","industry_name":"Lawyers/Law Firms","indivs":"15650","pacs":"4250","total":"19900"}},{"@attributes":{"industry_code":"N12","industry_name":"Misc Business","indivs":"16675","pacs":"0","total":"16675"}},{"@attributes":{"industry_code":"F11","industry_name":"Accountants","indivs":"1925","pacs":"14500","total":"16425"}},{"@attributes":{"industry_code":"H01","industry_name":"Health Professionals","indivs":"11230","pacs":"0","total":"11230"}},{"@attributes":{"industry_code":"Q03","industry_name":"Leadership PACs","indivs":"0","pacs":"10500","total":"10500"}},{"@attributes":{"industry_code":"F09","industry_name":"Insurance","indivs":"4350","pacs":"6000","total":"10350"}},{"@attributes":{"industry_code":"Q13","industry_name":"Gun Rights","indivs":"7200","pacs":"2500","total":"9700"}}]}}}