{"id":"G000576","title":"Representative","short_title":"Rep.","api_uri":"https://api.propublica.org/congress/v1/members/G000576.json","first_name":"Glenn","middle_name":null,"last_name":"Grothman","suffix":null,"date_of_birth":"1955-07-03","gender":"M","party":"R","leadership_role":null,"twitter_account":"RepGrothman","facebook_account":"RepGrothman","youtube_account":null,"govtrack_id":"412661","cspan_id":"77282","votesmart_id":"3493","icpsr_id":"21559","crp_id":"N00036409","google_entity_id":"/m/02pnsk2","fec_candidate_id":"H4WI06048","url":"https://grothman.house.gov","rss_url":null,"contact_form":null,"in_office":true,"dw_nominate":0.612,"ideal_point":null,"seniority":"4","next_election":"2018","total_votes":1111,"missed_votes":35,"total_present":0,"last_updated":"2018-09-19 12:00:53 -0400","ocd_id":"ocd-division/country:us/state:wi/cd:6","office":"1217 Longworth House Office Building","phone":"202-225-2476","fax":"202-225-2356","state":"WI","district":"6","at_large":false,"geoid":"5506","missed_votes_pct":3.15,"votes_with_party_pct":94.15,"response":{"industries":{"@attributes":{"cand_name":"Glenn S Grothman (R)","cid":"N00036409","cycle":"2018","origin":"Center for Responsive Politics","source":"https://www.opensecrets.org/members-of-congress/industries?cid=N00036409&cycle=2018","last_updated":"08/21/2018"},"industry":[{"@attributes":{"industry_code":"W06","industry_name":"Retired","indivs":"143846","pacs":"0","total":"143846"}},{"@attributes":{"industry_code":"Q03","industry_name":"Leadership PACs","indivs":"0","pacs":"77200","total":"77200"}},{"@attributes":{"industry_code":"F09","industry_name":"Insurance","indivs":"11650","pacs":"60500","total":"72150"}},{"@attributes":{"industry_code":"F10","industry_name":"Real Estate","indivs":"56800","pacs":"6000","total":"62800"}},{"@attributes":{"industry_code":"Q05","industry_name":"Pro-Israel","indivs":"31900","pacs":"12500","total":"44400"}},{"@attributes":{"industry_code":"N15","industry_name":"Misc Manufacturing & Distributing","indivs":"17750","pacs":"17000","total":"34750"}},{"@attributes":{"industry_code":"K01","industry_name":"Lawyers/Law Firms","indivs":"26218","pacs":"7000","total":"33218"}},{"@attributes":{"industry_code":"F07","industry_name":"Securities & Investment","indivs":"22500","pacs":"10500","total":"33000"}},{"@attributes":{"industry_code":"M02","industry_name":"Automotive","indivs":"14050","pacs":"15500","total":"29550"}},{"@attributes":{"industry_code":"A01","industry_name":"Crop Production & Basic Processing","indivs":"1550","pacs":"26000","total":"27550"}}]}}}