{"id":"H001052","title":"Representative","short_title":"Rep.","api_uri":"https://api.propublica.org/congress/v1/members/H001052.json","first_name":"Andy","middle_name":null,"last_name":"Harris","suffix":null,"date_of_birth":"1957-01-25","gender":"M","party":"R","leadership_role":null,"twitter_account":"RepAndyHarrisMD","facebook_account":"AndyHarrisMD","youtube_account":"RepAndyHarris","govtrack_id":"412434","cspan_id":"1033464","votesmart_id":"19157","icpsr_id":"21139","crp_id":"N00029147","google_entity_id":"/m/02852wc","fec_candidate_id":"H8MD01094","url":"https://harris.house.gov","rss_url":"https://harris.house.gov/rss.xml","contact_form":null,"in_office":false,"dw_nominate":0.605,"ideal_point":null,"seniority":"6","next_election":"2016","total_votes":1325,"missed_votes":16,"total_present":0,"last_updated":"2018-07-08 18:10:16 -0400","ocd_id":"ocd-division/country:us/state:md/cd:1","office":null,"phone":null,"fax":null,"state":"MD","district":"1","at_large":false,"geoid":"2401","missed_votes_pct":1.21,"votes_with_party_pct":92.9,"response":{"industries":{"@attributes":{"cand_name":"Andy Harris (R)","cid":"N00029147","cycle":"2016","origin":"Center for Responsive Politics","source":"https://www.opensecrets.org/members-of-congress/industries?cid=N00029147&cycle=2016","last_updated":"11/27/2017"},"industry":[{"@attributes":{"industry_code":"H01","industry_name":"Health Professionals","indivs":"128802","pacs":"124200","total":"253002"}},{"@attributes":{"industry_code":"W06","industry_name":"Retired","indivs":"73347","pacs":"0","total":"73347"}},{"@attributes":{"industry_code":"F10","industry_name":"Real Estate","indivs":"42725","pacs":"7000","total":"49725"}},{"@attributes":{"industry_code":"N01","industry_name":"Food & Beverage","indivs":"23700","pacs":"12000","total":"35700"}},{"@attributes":{"industry_code":"D03","industry_name":"Misc Defense","indivs":"5900","pacs":"22000","total":"27900"}},{"@attributes":{"industry_code":"A09","industry_name":"Food Processing & Sales","indivs":"2750","pacs":"24500","total":"27250"}},{"@attributes":{"industry_code":"K01","industry_name":"Lawyers/Law Firms","indivs":"23532","pacs":"3000","total":"26532"}},{"@attributes":{"industry_code":"W04","industry_name":"Education","indivs":"22650","pacs":"1000","total":"23650"}},{"@attributes":{"industry_code":"A02","industry_name":"Tobacco","indivs":"500","pacs":"20807","total":"21307"}},{"@attributes":{"industry_code":"E01","industry_name":"Oil & Gas","indivs":"1500","pacs":"19000","total":"20500"}}]}}}