{"id":"H001036","title":"Representative","short_title":"Rep.","api_uri":"https://api.propublica.org/congress/v1/members/H001036.json","first_name":"Jeb","middle_name":null,"last_name":"Hensarling","suffix":null,"date_of_birth":"1957-05-29","gender":"M","party":"R","leadership_role":null,"twitter_account":"RepHensarling","facebook_account":"RepHensarling","youtube_account":"repjebhensarling","govtrack_id":"400175","cspan_id":"1003619","votesmart_id":"49827","icpsr_id":"20352","crp_id":"N00024922","google_entity_id":"/m/0h23n6","fec_candidate_id":"H2TX05121","url":"https://hensarling.house.gov","rss_url":"https://hensarling.house.gov/rss.xml","contact_form":null,"in_office":false,"dw_nominate":null,"ideal_point":null,"seniority":"14","next_election":"2016","total_votes":1325,"missed_votes":15,"total_present":0,"ocd_id":"ocd-division/country:us/state:tx/cd:5","office":null,"phone":null,"fax":null,"state":"TX","district":"5","at_large":false,"geoid":"4805","missed_votes_pct":1.13,"votes_with_party_pct":96.72,"response":{"industries":{"@attributes":{"cand_name":"Jeb Hensarling (R)","cid":"N00024922","cycle":"2016","origin":"Center for Responsive Politics","source":"https://www.opensecrets.org/members-of-congress/industries?cid=N00024922&cycle=2016","last_updated":"11/27/2017"},"industry":[{"@attributes":{"industry_code":"F07","industry_name":"Securities & Investment","indivs":"113745","pacs":"185000","total":"298745"}},{"@attributes":{"industry_code":"F09","industry_name":"Insurance","indivs":"41700","pacs":"240000","total":"281700"}},{"@attributes":{"industry_code":"F03","industry_name":"Commercial Banks","indivs":"72700","pacs":"199600","total":"272300"}},{"@attributes":{"industry_code":"F10","industry_name":"Real Estate","indivs":"46750","pacs":"112500","total":"159250"}},{"@attributes":{"industry_code":"F13","industry_name":"Misc Finance","indivs":"65850","pacs":"42000","total":"107850"}},{"@attributes":{"industry_code":"W06","industry_name":"Retired","indivs":"93581","pacs":"0","total":"93581"}},{"@attributes":{"industry_code":"F06","industry_name":"Finance/Credit Companies","indivs":"15700","pacs":"67500","total":"83200"}},{"@attributes":{"industry_code":"K01","industry_name":"Lawyers/Law Firms","indivs":"40700","pacs":"39650","total":"80350"}},{"@attributes":{"industry_code":"E01","industry_name":"Oil & Gas","indivs":"15400","pacs":"44000","total":"59400"}},{"@attributes":{"industry_code":"F11","industry_name":"Accountants","indivs":"2300","pacs":"55000","total":"57300"}}]}}}