{"id":"L000580","title":"Representative","short_title":"Rep.","api_uri":"https://api.propublica.org/congress/v1/members/L000580.json","first_name":"Michelle","middle_name":null,"last_name":"Lujan Grisham","suffix":null,"date_of_birth":"1959-10-24","gender":"F","party":"D","leadership_role":null,"twitter_account":"RepLujanGrisham","facebook_account":"RepLujanGrisham","youtube_account":"RepLujanGrisham","govtrack_id":"412558","cspan_id":"94791","votesmart_id":"102404","icpsr_id":"21341","crp_id":"N00029400","google_entity_id":"/m/0n3vkrv","fec_candidate_id":"","url":"https://lujangrisham.house.gov","rss_url":null,"contact_form":null,"in_office":false,"dw_nominate":-0.314,"ideal_point":-0.793332132,"seniority":"2","total_votes":1192,"missed_votes":33,"total_present":1,"last_updated":"2018-07-08 18:13:01 -0400","ocd_id":"ocd-division/country:us/state:nm/cd:1","office":null,"phone":null,"fax":null,"state":"NM","district":"1","at_large":false,"geoid":"3501","missed_votes_pct":2.77,"votes_with_party_pct":92.32,"response":{"industries":{"@attributes":{"cand_name":"Michelle Lujan Grisham (D)","cid":"N00029400","cycle":"2014","origin":"Center for Responsive Politics","source":"https://www.opensecrets.org/members-of-congress/industries?cid=N00029400&cycle=2014","last_updated":"02/27/2017"},"industry":[{"@attributes":{"industry_code":"K01","industry_name":"Lawyers/Law Firms","indivs":"166480","pacs":"12000","total":"178480"}},{"@attributes":{"industry_code":"H01","industry_name":"Health Professionals","indivs":"17616","pacs":"142000","total":"159616"}},{"@attributes":{"industry_code":"W06","industry_name":"Retired","indivs":"67706","pacs":"0","total":"67706"}},{"@attributes":{"industry_code":"P04","industry_name":"Public Sector Unions","indivs":"0","pacs":"67500","total":"67500"}},{"@attributes":{"industry_code":"P01","industry_name":"Building Trade Unions","indivs":"0","pacs":"61000","total":"61000"}},{"@attributes":{"industry_code":"P02","industry_name":"Industrial Unions","indivs":"0","pacs":"51000","total":"51000"}},{"@attributes":{"industry_code":"Q03","industry_name":"Leadership PACs","indivs":"0","pacs":"45000","total":"45000"}},{"@attributes":{"industry_code":"F09","industry_name":"Insurance","indivs":"12650","pacs":"31000","total":"43650"}},{"@attributes":{"industry_code":"K02","industry_name":"Lobbyists","indivs":"41049","pacs":"0","total":"41049"}},{"@attributes":{"industry_code":"Q08","industry_name":"Women's Issues","indivs":"36975","pacs":"500","total":"37475"}}]}}}