{"id":"M001137","title":"Representative","short_title":"Rep.","api_uri":"https://api.propublica.org/congress/v1/members/M001137.json","first_name":"Gregory","middle_name":"W.","last_name":"Meeks","suffix":null,"date_of_birth":"1953-09-25","gender":"M","party":"D","leadership_role":null,"twitter_account":"RepGregoryMeeks","facebook_account":"RepGregoryMeeks","youtube_account":"repgregorymeeks","govtrack_id":"400271","cspan_id":"53469","votesmart_id":"4360","icpsr_id":"29776","crp_id":"N00001171","google_entity_id":"/m/024_3b","fec_candidate_id":"","url":"https://meeks.house.gov","rss_url":"https://meeks.house.gov/rss.xml","contact_form":null,"in_office":false,"dw_nominate":-0.412,"ideal_point":-1.089883079,"seniority":"18","next_election":"2014","total_votes":1192,"missed_votes":86,"total_present":1,"last_updated":"2018-07-08 18:13:08 -0400","ocd_id":"ocd-division/country:us/state:ny/cd:5","office":null,"phone":null,"fax":null,"state":"NY","district":"5","at_large":false,"geoid":"3605","missed_votes_pct":7.21,"votes_with_party_pct":94.67,"response":{"industries":{"@attributes":{"cand_name":"Gregory W Meeks (D)","cid":"N00001171","cycle":"2014","origin":"Center for Responsive Politics","source":"https://www.opensecrets.org/members-of-congress/industries?cid=N00001171&cycle=2014","last_updated":"02/27/2017"},"industry":[{"@attributes":{"industry_code":"F07","industry_name":"Securities & Investment","indivs":"25309","pacs":"101000","total":"126309"}},{"@attributes":{"industry_code":"F09","industry_name":"Insurance","indivs":"0","pacs":"119300","total":"119300"}},{"@attributes":{"industry_code":"F06","industry_name":"Finance/Credit Companies","indivs":"17250","pacs":"66000","total":"83250"}},{"@attributes":{"industry_code":"F10","industry_name":"Real Estate","indivs":"9600","pacs":"58049","total":"67649"}},{"@attributes":{"industry_code":"F03","industry_name":"Commercial Banks","indivs":"1725","pacs":"58000","total":"59725"}},{"@attributes":{"industry_code":"K01","industry_name":"Lawyers/Law Firms","indivs":"19000","pacs":"22912","total":"41912"}},{"@attributes":{"industry_code":"F11","industry_name":"Accountants","indivs":"0","pacs":"35500","total":"35500"}},{"@attributes":{"industry_code":"N04","industry_name":"Misc Services","indivs":"8650","pacs":"23500","total":"32150"}},{"@attributes":{"industry_code":"M01","industry_name":"Air Transport","indivs":"0","pacs":"29500","total":"29500"}},{"@attributes":{"industry_code":"K02","industry_name":"Lobbyists","indivs":"25117","pacs":"3500","total":"28617"}}]}}}