{"id":"N000181","title":"Representative","short_title":"Rep.","api_uri":"https://api.propublica.org/congress/v1/members/N000181.json","first_name":"Devin","middle_name":null,"last_name":"Nunes","suffix":null,"date_of_birth":"1973-10-01","gender":"M","party":"R","leadership_role":null,"twitter_account":"Rep_DevinNunes","facebook_account":null,"youtube_account":"RepDevinNunes","govtrack_id":"400297","cspan_id":"1003553","votesmart_id":"16725","icpsr_id":"20307","crp_id":"N00007248","google_entity_id":"/m/024tds","fec_candidate_id":"","url":"https://nunes.house.gov","rss_url":"http://feeds.feedburner.com/RepDevinNunes?format=xml","contact_form":null,"in_office":false,"dw_nominate":null,"ideal_point":null,"seniority":"10","next_election":"2012","total_votes":1606,"missed_votes":27,"total_present":0,"ocd_id":"ocd-division/country:us/state:ca/cd:21","office":null,"phone":null,"fax":null,"state":"CA","district":"21","at_large":false,"geoid":"0621","missed_votes_pct":1.68,"votes_with_party_pct":94.3,"response":{"industries":{"@attributes":{"cand_name":"Devin Nunes (R)","cid":"N00007248","cycle":"2012","origin":"Center for Responsive Politics","source":"https://www.opensecrets.org/members-of-congress/industries?cid=N00007248&cycle=2012","last_updated":"03/25/2013"},"industry":[{"@attributes":{"industry_code":"A01","industry_name":"Crop Production & Basic Processing","indivs":"208600","pacs":"52250","total":"260850"}},{"@attributes":{"industry_code":"A04","industry_name":"Dairy","indivs":"58250","pacs":"31000","total":"89250"}},{"@attributes":{"industry_code":"F09","industry_name":"Insurance","indivs":"9750","pacs":"75000","total":"84750"}},{"@attributes":{"industry_code":"H04","industry_name":"Pharmaceuticals/Health Products","indivs":"3000","pacs":"75500","total":"78500"}},{"@attributes":{"industry_code":"H01","industry_name":"Health Professionals","indivs":"17050","pacs":"56500","total":"73550"}},{"@attributes":{"industry_code":"F07","industry_name":"Securities & Investment","indivs":"8500","pacs":"55000","total":"63500"}},{"@attributes":{"industry_code":"A07","industry_name":"Agricultural Services/Products","indivs":"31250","pacs":"22500","total":"53750"}},{"@attributes":{"industry_code":"N07","industry_name":"Casinos/Gambling","indivs":"38450","pacs":"12500","total":"50950"}},{"@attributes":{"industry_code":"E01","industry_name":"Oil & Gas","indivs":"250","pacs":"48250","total":"48500"}},{"@attributes":{"industry_code":"N02","industry_name":"Beer, Wine & Liquor","indivs":"0","pacs":"41248","total":"41248"}}]}}}