{"id":"P000603","title":"Senator, 3rd Class","short_title":"Sen.","api_uri":"https://api.propublica.org/congress/v1/members/P000603.json","first_name":"Rand","middle_name":null,"last_name":"Paul","suffix":null,"date_of_birth":"1963-01-07","gender":"M","party":"R","leadership_role":null,"twitter_account":null,"facebook_account":"SenatorRandPaul","youtube_account":"SenatorRandPaul","govtrack_id":"412492","cspan_id":"9265241","votesmart_id":"117285","icpsr_id":"41104","crp_id":"N00030836","google_entity_id":"/m/05pdb7q","fec_candidate_id":"S0KY00156","url":"https://www.paul.senate.gov","rss_url":null,"contact_form":"https://www.paul.senate.gov/connect/email-rand","in_office":true,"dw_nominate":0.872,"ideal_point":null,"seniority":"7","next_election":"2022","total_votes":388,"missed_votes":14,"total_present":0,"ocd_id":"ocd-division/country:us/state:ky","office":"167 Russell Senate Office Building","phone":"202-224-4343","fax":"202-228-1373","state":"KY","senate_class":"3","state_rank":"junior","lis_id":"S348","missed_votes_pct":3.61,"votes_with_party_pct":83.69,"response":{"industries":{"@attributes":{"cand_name":"Rand Paul (R)","cid":"N00030836","cycle":"2016","origin":"Center for Responsive Politics","source":"https://www.opensecrets.org/members-of-congress/industries?cid=N00030836&cycle=2016","last_updated":"11/27/2017"},"industry":[{"@attributes":{"industry_code":"W06","industry_name":"Retired","indivs":"779701","pacs":"0","total":"779701"}},{"@attributes":{"industry_code":"H01","industry_name":"Health Professionals","indivs":"516792","pacs":"81500","total":"598292"}},{"@attributes":{"industry_code":"Q01","industry_name":"Republican/Conservative","indivs":"395111","pacs":"34265","total":"429376"}},{"@attributes":{"industry_code":"F07","industry_name":"Securities & Investment","indivs":"369533","pacs":"19000","total":"388533"}},{"@attributes":{"industry_code":"F10","industry_name":"Real Estate","indivs":"225623","pacs":"17500","total":"243123"}},{"@attributes":{"industry_code":"Q03","industry_name":"Leadership PACs","indivs":"0","pacs":"224000","total":"224000"}},{"@attributes":{"industry_code":"K01","industry_name":"Lawyers/Law Firms","indivs":"173407","pacs":"22500","total":"195907"}},{"@attributes":{"industry_code":"F13","industry_name":"Misc Finance","indivs":"185667","pacs":"5200","total":"190867"}},{"@attributes":{"industry_code":"E04","industry_name":"Mining","indivs":"122800","pacs":"15650","total":"138450"}},{"@attributes":{"industry_code":"F09","industry_name":"Insurance","indivs":"80136","pacs":"51500","total":"131636"}}]}}}