{"id":"P000607","title":"Representative","short_title":"Rep.","api_uri":"https://api.propublica.org/congress/v1/members/P000607.json","first_name":"Mark","middle_name":null,"last_name":"Pocan","suffix":null,"date_of_birth":"1964-08-14","gender":"M","party":"D","leadership_role":null,"twitter_account":"RepMarkPocan","facebook_account":"repmarkpocan","youtube_account":"repmarkpocan","govtrack_id":"412585","cspan_id":"79688","votesmart_id":"26238","icpsr_id":"21370","crp_id":"N00033549","google_entity_id":"/m/0gyhpz","fec_candidate_id":"H2WI02124","url":"https://pocan.house.gov","rss_url":"https://pocan.house.gov/rss.xml","contact_form":null,"in_office":true,"dw_nominate":-0.552,"ideal_point":null,"seniority":"6","next_election":"2018","total_votes":841,"missed_votes":130,"total_present":0,"ocd_id":"ocd-division/country:us/state:wi/cd:2","office":"1421 Longworth House Office Building","phone":"202-225-2906","fax":"202-225-6942","state":"WI","district":"2","at_large":false,"geoid":"5502","missed_votes_pct":15.46,"votes_with_party_pct":94.23,"response":{"industries":{"@attributes":{"cand_name":"Mark Pocan (D)","cid":"N00033549","cycle":"2012","origin":"Center for Responsive Politics","source":"https://www.opensecrets.org/members-of-congress/industries?cid=N00033549&cycle=2012","last_updated":"03/25/2013"},"industry":[{"@attributes":{"industry_code":"P01","industry_name":"Building Trade Unions","indivs":"0","pacs":"79000","total":"79000"}},{"@attributes":{"industry_code":"P04","industry_name":"Public Sector Unions","indivs":"950","pacs":"67500","total":"68450"}},{"@attributes":{"industry_code":"H01","industry_name":"Health Professionals","indivs":"5200","pacs":"51000","total":"56200"}},{"@attributes":{"industry_code":"W06","industry_name":"Retired","indivs":"47900","pacs":"0","total":"47900"}},{"@attributes":{"industry_code":"K01","industry_name":"Lawyers/Law Firms","indivs":"30850","pacs":"11000","total":"41850"}},{"@attributes":{"industry_code":"P02","industry_name":"Industrial Unions","indivs":"500","pacs":"38000","total":"38500"}},{"@attributes":{"industry_code":"F10","industry_name":"Real Estate","indivs":"21750","pacs":"12500","total":"34250"}},{"@attributes":{"industry_code":"Q09","industry_name":"Human Rights","indivs":"12500","pacs":"19865","total":"32365"}},{"@attributes":{"industry_code":"W04","industry_name":"Education","indivs":"24750","pacs":"1000","total":"25750"}},{"@attributes":{"industry_code":"K02","industry_name":"Lobbyists","indivs":"24088","pacs":"1500","total":"25588"}}]}}}