{"id":"T000250","title":"Senator, 3rd Class","short_title":"Sen.","api_uri":"https://api.propublica.org/congress/v1/members/T000250.json","first_name":"John","middle_name":null,"last_name":"Thune","suffix":null,"date_of_birth":"1961-01-07","gender":"M","party":"R","leadership_role":"Conference Chair","twitter_account":"SenJohnThune","facebook_account":null,"youtube_account":"johnthune","govtrack_id":"400546","cspan_id":"45552","votesmart_id":"398","icpsr_id":"29754","crp_id":"N00004572","google_entity_id":"/m/03ybyn","fec_candidate_id":"S2SD00068","url":"https://www.thune.senate.gov","rss_url":"https://www.thune.senate.gov/public/?a=RSS.Feed","contact_form":"http://www.thune.senate.gov/public/index.cfm/contact","in_office":true,"dw_nominate":0.409,"ideal_point":null,"seniority":"13","next_election":"2022","total_votes":388,"missed_votes":0,"total_present":0,"ocd_id":"ocd-division/country:us/state:sd","office":"511 Dirksen Senate Office Building","phone":"202-224-2321","fax":"202-228-5429","state":"SD","senate_class":"3","state_rank":"senior","lis_id":"S303","missed_votes_pct":0,"votes_with_party_pct":98.71,"response":{"industries":{"@attributes":{"cand_name":"John Thune (R)","cid":"N00004572","cycle":"2012","origin":"Center for Responsive Politics","source":"https://www.opensecrets.org/members-of-congress/industries?cid=N00004572&cycle=2012","last_updated":"03/25/2013"},"industry":[{"@attributes":{"industry_code":"W06","industry_name":"Retired","indivs":"955734","pacs":"0","total":"955734"}},{"@attributes":{"industry_code":"F07","industry_name":"Securities & Investment","indivs":"292990","pacs":"83000","total":"375990"}},{"@attributes":{"industry_code":"F09","industry_name":"Insurance","indivs":"127410","pacs":"244500","total":"371910"}},{"@attributes":{"industry_code":"F10","industry_name":"Real Estate","indivs":"280527","pacs":"49010","total":"329537"}},{"@attributes":{"industry_code":"K02","industry_name":"Lobbyists","indivs":"288096","pacs":"8398","total":"296494"}},{"@attributes":{"industry_code":"K01","industry_name":"Lawyers/Law Firms","indivs":"189629","pacs":"87422","total":"277051"}},{"@attributes":{"industry_code":"Q01","industry_name":"Republican/Conservative","indivs":"239766","pacs":"19977","total":"259743"}},{"@attributes":{"industry_code":"H01","industry_name":"Health Professionals","indivs":"176913","pacs":"73500","total":"250413"}},{"@attributes":{"industry_code":"F03","industry_name":"Commercial Banks","indivs":"141730","pacs":"86700","total":"228430"}},{"@attributes":{"industry_code":"F13","industry_name":"Misc Finance","indivs":"175804","pacs":"30500","total":"206304"}}]}}}