{"id":"W000810","title":"Representative","short_title":"Rep.","api_uri":"https://api.propublica.org/congress/v1/members/W000810.json","first_name":"Rob","middle_name":null,"last_name":"Woodall","suffix":null,"date_of_birth":"1970-02-11","gender":"M","party":"R","leadership_role":null,"twitter_account":"RepRobWoodall","facebook_account":"RepRobWoodall","youtube_account":"RobWoodallGA07","govtrack_id":"412416","cspan_id":"623342","votesmart_id":"122251","icpsr_id":"21122","crp_id":"N00032416","google_entity_id":"/m/0cz8ryh","fec_candidate_id":"H0GA07133","url":"https://woodall.house.gov","rss_url":"https://woodall.house.gov/rss.xml","contact_form":null,"in_office":true,"dw_nominate":0.65,"ideal_point":null,"seniority":"8","next_election":"2018","total_votes":841,"missed_votes":10,"total_present":0,"ocd_id":"ocd-division/country:us/state:ga/cd:7","office":"1724 Longworth House Office Building","phone":"202-225-4272","fax":"202-225-4696","state":"GA","district":"7","at_large":false,"geoid":"1307","missed_votes_pct":1.19,"votes_with_party_pct":93.62,"response":{"industries":{"@attributes":{"cand_name":"Rob Woodall (R)","cid":"N00032416","cycle":"2016","origin":"Center for Responsive Politics","source":"https://www.opensecrets.org/members-of-congress/industries?cid=N00032416&cycle=2016","last_updated":"11/27/2017"},"industry":[{"@attributes":{"industry_code":"M01","industry_name":"Air Transport","indivs":"2700","pacs":"57000","total":"59700"}},{"@attributes":{"industry_code":"C05","industry_name":"Building Materials & Equipment","indivs":"14300","pacs":"25250","total":"39550"}},{"@attributes":{"industry_code":"H01","industry_name":"Health Professionals","indivs":"15300","pacs":"23500","total":"38800"}},{"@attributes":{"industry_code":"F09","industry_name":"Insurance","indivs":"500","pacs":"36500","total":"37000"}},{"@attributes":{"industry_code":"F10","industry_name":"Real Estate","indivs":"22261","pacs":"8500","total":"30761"}},{"@attributes":{"industry_code":"M04","industry_name":"Railroads","indivs":"2250","pacs":"22000","total":"24250"}},{"@attributes":{"industry_code":"F05","industry_name":"Credit Unions","indivs":"11350","pacs":"10000","total":"21350"}},{"@attributes":{"industry_code":"F03","industry_name":"Commercial Banks","indivs":"1250","pacs":"20000","total":"21250"}},{"@attributes":{"industry_code":"E01","industry_name":"Oil & Gas","indivs":"0","pacs":"18500","total":"18500"}},{"@attributes":{"industry_code":"C01","industry_name":"General Contractors","indivs":"10350","pacs":"7500","total":"17850"}}]}}}